realtimeconfig/__init__.py
realtimeconfig/monitor.py
realtimeconfig-0.0.1.dist-info/LICENSE
realtimeconfig-0.0.1.dist-info/METADATA
realtimeconfig-0.0.1.dist-info/WHEEL
realtimeconfig-0.0.1.dist-info/entry_points.txt
realtimeconfig-0.0.1.dist-info/top_level.txt
realtimeconfig-0.0.1.dist-info/RECORD
