Metadata-Version: 2.1
Name: realtimeconfig
Version: 0.0.1
Summary: UNKNOWN
Home-page: https://realtimeconfig.com
License: UNKNOWN
Platform: UNKNOWN
Classifier: Programming Language :: Python :: 3
Classifier: License :: OSI Approved :: MIT License
Classifier: Operating System :: OS Independent
License-File: LICENSE
Requires-Dist: websocket-client
